mostpopularnewscnn/__init__.py
mostpopularnewscnn_kesuma-0.0.1.dist-info/LICENSE
mostpopularnewscnn_kesuma-0.0.1.dist-info/METADATA
mostpopularnewscnn_kesuma-0.0.1.dist-info/WHEEL
mostpopularnewscnn_kesuma-0.0.1.dist-info/top_level.txt
mostpopularnewscnn_kesuma-0.0.1.dist-info/RECORD
