Metadata-Version: 2.1
Name: mostpopularnewscnn-kesuma
Version: 0.0.1
Summary: This package will get the most popular news in CNN Indonesia
Author-email: Tri Praseto Kusumo Aji <ajikprasetyo22@gmail.com>
Project-URL: Homepage, https://github.com/jetkesuma/most-popular-news-cnn-id
Project-URL: Medium, https://medium.com/@kusumo999666
Classifier: Programming Language :: Python :: 3
Classifier: License :: OSI Approved :: GNU General Public License v3 (GPLv3)
Classifier: Operating System :: OS Independent
Classifier: Development Status :: 5 - Production/Stable
Requires-Python: >=3.7
License-File: LICENSE
